<?xml version="1.0"?>
<!DOCTYPE hibernate-mapping PUBLIC
      "-//Hibernate/Hibernate Mapping DTD 3.0//EN"
          "http://www.hibernate.org/dtd/hibernate-mapping-3.0.dtd">
          
<hibernate-mapping package="org.esupportail.opi.domain.beans.parameters.accessRight">

	<class name="AccessRight" table="access_right">
		<id name="id" unsaved-value="null"> 
			<column name="id_ac_right" not-null="true"/>
			<generator class="native" >
				<param name="sequence">access_right_seq</param>
			</generator>
		</id>
		<property name="codeAccessType" column="cod_ac_typ"/>
		<many-to-one name="traitement" column="id_trt" not-null="true" />
		<many-to-one name="profile" column="id_pro" not-null="true" />
	</class>	
</hibernate-mapping>


